mem_common/__init__.py
mem_common/config.py
mem_common/db/__init__.py
mem_common/db/engine.py
mem_common/db/models.py
mem_common/models/__init__.py
mem_common/models/request.py
mem_common/models/service.py
mem_common-0.1.2.dist-info/WHEEL
mem_common-0.1.2.dist-info/METADATA
mem_common-0.1.2.dist-info/RECORD
