Metadata-Version: 2.3
Name: mem-common
Version: 0.1.2
Summary: Shared configuration, models, and database utilities for memrun
Author: Julian Mulla
Author-email: Julian Mulla <jmulla@gmail.com>
Requires-Dist: pydantic>=2.0
Requires-Dist: pydantic-settings>=2.0
Requires-Dist: sqlalchemy[asyncio]>=2.0
Requires-Dist: asyncpg>=0.29
Requires-Python: >=3.11
